packagebuilder/__init__.py
packagebuilder/_pip.py
packagebuilder/_pip_shims.py
packagebuilder/build.py
packagebuilder-0.1.0.dist-info/METADATA
packagebuilder-0.1.0.dist-info/RECORD
packagebuilder-0.1.0.dist-info/WHEEL
packagebuilder-0.1.0.dist-info/top_level.txt
packagebuilder-0.1.0.dist-info/zip-safe
