Metadata-Version: 2.1
Name: packagebuilder
Version: 0.1.0
Summary: A library for building python packages into binary or source distributions.
Home-page: https://github.com/sarugaku/packagebuilder
Author: Dan Ryan and Tzu-ping Chung
Author-email: dan@danryan.co
License: ISC License
Keywords: package management,resolver,pipenv,requirementslib,pipfile,dependencies,dependency management,package builder,package building
Platform: UNKNOWN
Classifier: Development Status :: 1 - Planning
Classifier: License :: OSI Approved :: ISC License (ISCL)
Classifier: Operating System :: OS Independent
Classifier: Programming Language :: Python :: 2
Classifier: Programming Language :: Python :: 2.6
Classifier: Programming Language :: Python :: 2.7
Classifier: Programming Language :: Python :: 3
Classifier: Programming Language :: Python :: 3.4
Classifier: Programming Language :: Python :: 3.5
Classifier: Programming Language :: Python :: 3.6
Classifier: Programming Language :: Python :: 3.7
Classifier: Topic :: Software Development :: Libraries :: Python Modules
Requires-Python: >=2.6,!=3.0,!=3.1,!=3.2,!=3.3
Provides-Extra: tests
